API_Gen/__init__.py
API_Gen/__main__.py
API_Gen/base_generator.py
API_Gen/exceptions.py
API_Gen/flask_generator.py
API_Gen/sanic_generator.py
REST_API_Generator-1.1.1.dist-info/LICENSE
REST_API_Generator-1.1.1.dist-info/METADATA
REST_API_Generator-1.1.1.dist-info/WHEEL
REST_API_Generator-1.1.1.dist-info/top_level.txt
REST_API_Generator-1.1.1.dist-info/RECORD
