Metadata-Version: 2.1
Name: REST-API-Generator
Version: 1.1.1
Summary: Package designed to generate REST API layer
Home-page: https://github.com/PhaniKumarGudepu/API_Gen
Author: Phani Kumar Gudepu
Author-email: phanigudepu333@gmail.com
License: MIT License
Keywords: python,API,REST,API layer,dummy API,generator,sanic,flask,framework
Classifier: Development Status :: 4 - Beta
Classifier: Intended Audience :: Developers
Classifier: Programming Language :: Python :: 3
Classifier: Operating System :: Unix
Classifier: Operating System :: MacOS :: MacOS X
Classifier: Operating System :: Microsoft :: Windows
Requires-Python: >=3.6
License-File: LICENSE
